{
  "users": [
    {
      "id": 1,
      "name": "Pedro",
      "email": "pedro@mail.com"
    },
    {
      "id": 2,
      "name": "Paulo",
      "email": "paulo@mail.com"
    },
    {
      "id": 3,
      "name": "João",
      "email": "joao@mail.com"
    }
  ],
  "toDos": [
    {
      "id": 1,
      "title": "Fazer API",
      "status": "pendente",
      "userId": 1
    },
    {
      "id": 2,
      "title": "Fazer Front-End",
      "status": "pendente",
      "userId": 1
    },
    {
      "id": 3,
      "title": "Construir documentação",
      "status": "concluído",
      "userId": 2
    },
    {
      "id": 4,
      "title": "Imprimir currículos",
      "status": "concluído",
      "userId": 3
    },
    {
      "id": 5,
      "title": "Distribiur currículos",
      "status": "pendente",
      "userId": 3
    }
  ]
}
